README.md
setup.cfg
setup.py
dawa/__init__.py
dawa/api.py
dawa/endpoints.py
dawa/enums.py
dawa/exceptions.py
dawa_sdk.egg-info/PKG-INFO
dawa_sdk.egg-info/SOURCES.txt
dawa_sdk.egg-info/dependency_links.txt
dawa_sdk.egg-info/requires.txt
dawa_sdk.egg-info/top_level.txt
tests/__init__.py
tests/test_adgangsadresse.py
tests/test_adresse.py
tests/test_afstemningsområde.py
tests/test_afstemningsområdetilknytning.py
tests/test_brofasthed.py
tests/test_bygning.py
tests/test_bygningtilknytning.py
tests/test_dagi_postnummer.py
tests/test_ejerlav.py
tests/test_højde.py
tests/test_ikke_brofast_husnummer.py
tests/test_jordstykke.py
tests/test_jordstykketilknytning.py
tests/test_kommune.py
tests/test_kommunetilknytning.py
tests/test_landpostnummer.py
tests/test_menighedsrådsafstemningsområde.py
tests/test_menighedsrådsafstemningsområdetilknytning.py
tests/test_navngivenvej.py
tests/test_opstillingskreds.py
tests/test_opstillingskredstilknytning.py
tests/test_politikreds.py
tests/test_politikredstilknytning.py
tests/test_postnummer.py
tests/test_region.py
tests/test_regionstilknytning.py
tests/test_retskreds.py
tests/test_retskredstilknytning.py
tests/test_sogn.py
tests/test_sognetilknytning.py
tests/test_sted.py
tests/test_stednavn.py
tests/test_stednavntilknytning.py
tests/test_stedtilknytning.py
tests/test_storkreds.py
tests/test_storkredstilknytning.py
tests/test_supplerendebynavn.py
tests/test_supplerendebynavntilknytning.py
tests/test_txid.py
tests/test_valglandsdel.py
tests/test_valglandsdelstilknytning.py
tests/test_vejmidte.py
tests/test_vejpunkt.py
tests/test_vejstykke.py
tests/test_vejstykkepostnummerrelation.py
tests/test_zone.py
tests/test_zonetilknytning.py