Metadata-Version: 2.1
Name: dawa-sdk
Version: 0.2.5
Summary: Python Dawa API
Home-page: https://github.com/Fredehagelund92/dawa-sdk
Author: Frederik Hagelund
Author-email: frederik.hagelund@gmail.com
License: GPL
Keywords: dawa,api,python
Platform: UNKNOWN
Classifier: Development Status :: 4 - Beta
Classifier: Intended Audience :: Developers
Classifier: Operating System :: OS Independent
Classifier: Programming Language :: Python :: 3.7
Classifier: Operating System :: OS Independent
Classifier: Topic :: Software Development :: Libraries :: Python Modules
